
{
  "name": "Python DevContainer",

  "image": "mcr.microsoft.com/devcontainers/python:3.11",

  "features": {
    "ghcr.io/devcontainers/features/common-utils:1": {}
  },

  "customizations": {
    "vscode": {
      "extensions": [
        "ms-python.python",
        "ms-python.vscode-pylance",
        "ms-toolsai.jupyter"
      ],
      "settings": {
        "python.defaultInterpreterPath": "/usr/local/bin/python",
        "python.terminal.activateEnvironment": true,
        "python.terminal.activateEnvInCurrentTerminal": true
      }
    }
  },

  "postCreateCommand": ["sudo apt update && sudo apt install -y git-lfs && git lfs install", "pip install -r requirements.txt"],

  "remoteUser": "vscode",

  "mounts": [
    "source=devcontainer-cache,target=/root/.cache,type=volume"
  ]
}

